lifesospy/__init__.py
lifesospy/__main__.py
lifesospy/asynchelper.py
lifesospy/baseunit.py
lifesospy/client.py
lifesospy/command.py
lifesospy/const.py
lifesospy/contactid.py
lifesospy/device.py
lifesospy/devicecategory.py
lifesospy/deviceevent.py
lifesospy/enums.py
lifesospy/propertychangedinfo.py
lifesospy/protocol.py
lifesospy/response.py
lifesospy/server.py
lifesospy/util.py
lifesospy-0.10.1.dist-info/METADATA
lifesospy-0.10.1.dist-info/RECORD
lifesospy-0.10.1.dist-info/WHEEL
lifesospy-0.10.1.dist-info/top_level.txt
