Metadata-Version: 2.1
Name: lifesospy
Version: 0.10.1
Summary: Provides an interface to LifeSOS alarm systems.
Home-page: https://github.com/rorr73/lifesospy
Author: Richard Orr
License: UNKNOWN
Platform: UNKNOWN
Classifier: Development Status :: 3 - Alpha
Classifier: Environment :: Other Environment
Classifier: Intended Audience :: Developers
Classifier: Operating System :: OS Independent
Classifier: Programming Language :: Python
Classifier: Topic :: Home Automation
Classifier: Topic :: Software Development :: Libraries :: Python Modules
Requires-Python: >=3.5.3
Requires-Dist: aenum
